{
    "countries": [
        {
            "countryID": 1,
            "countryName": "bbb",
            "tower": {
                "floors": [
                    {
                        "floorNum": 0,
                        "floorSize": 12,
                        "buildings": [
                            {
                                "buildingID": 1,
                                "buildingObject": {
                                    "instanceID": 0
                                }
                            },
                            {
                                "buildingID": 2,
                                "buildingObject": {
                                    "instanceID": 0
                                }
                            },
                            {
                                "buildingID": 3,
                                "buildingObject": {
                                    "instanceID": 0
                                }
                            },
                            {
                                "buildingID": 4,
                                "buildingObject": {
                                    "instanceID": 0
                                }
                            },
                            {
                                "buildingID": 0,
                                "buildingObject": {
                                    "instanceID": 0
                                }
                            },
                            {
                                "buildingID": 0,
                                "buildingObject": {
                                    "instanceID": 0
                                }
                            }
                        ]
                    },
                    {
                        "floorNum": 1,
                        "floorSize": 11,
                        "buildings": [
                            {
                                "buildingID": 5,
                                "buildingObject": {
                                    "instanceID": 0
                                }
                            },
                            {
                                "buildingID": 6,
                                "buildingObject": {
                                    "instanceID": 0
                                }
                            },
                            {
                                "buildingID": 7,
                                "buildingObject": {
                                    "instanceID": 0
                                }
                            },
                            {
                                "buildingID": 8,
                                "buildingObject": {
                                    "instanceID": 0
                                }
                            },
                            {
                                "buildingID": 0,
                                "buildingObject": {
                                    "instanceID": 0
                                }
                            },
                            {
                                "buildingID": 0,
                                "buildingObject": {
                                    "instanceID": 0
                                }
                            }
                        ]
                    },
                    {
                        "floorNum": 2,
                        "floorSize": 10,
                        "buildings": [
                            {
                                "buildingID": 9,
                                "buildingObject": {
                                    "instanceID": 0
                                }
                            },
                            {
                                "buildingID": 10,
                                "buildingObject": {
                                    "instanceID": 0
                                }
                            },
                            {
                                "buildingID": 11,
                                "buildingObject": {
                                    "instanceID": 0
                                }
                            },
                            {
                                "buildingID": 12,
                                "buildingObject": {
                                    "instanceID": 0
                                }
                            },
                            {
                                "buildingID": 0,
                                "buildingObject": {
                                    "instanceID": 0
                                }
                            },
                            {
                                "buildingID": 0,
                                "buildingObject": {
                                    "instanceID": 0
                                }
                            }
                        ]
                    },
                    {
                        "floorNum": 3,
                        "floorSize": 9,
                        "buildings": [
                            {
                                "buildingID": 13,
                                "buildingObject": {
                                    "instanceID": 0
                                }
                            },
                            {
                                "buildingID": 14,
                                "buildingObject": {
                                    "instanceID": 0
                                }
                            },
                            {
                                "buildingID": 15,
                                "buildingObject": {
                                    "instanceID": 0
                                }
                            },
                            {
                                "buildingID": 0,
                                "buildingObject": {
                                    "instanceID": 0
                                }
                            },
                            {
                                "buildingID": 0,
                                "buildingObject": {
                                    "instanceID": 0
                                }
                            },
                            {
                                "buildingID": 0,
                                "buildingObject": {
                                    "instanceID": 0
                                }
                            }
                        ]
                    },
                    {
                        "floorNum": 4,
                        "floorSize": 8,
                        "buildings": [
                            {
                                "buildingID": 16,
                                "buildingObject": {
                                    "instanceID": 0
                                }
                            },
                            {
                                "buildingID": 17,
                                "buildingObject": {
                                    "instanceID": 0
                                }
                            },
                            {
                                "buildingID": 0,
                                "buildingObject": {
                                    "instanceID": 0
                                }
                            },
                            {
                                "buildingID": 0,
                                "buildingObject": {
                                    "instanceID": 0
                                }
                            },
                            {
                                "buildingID": 0,
                                "buildingObject": {
                                    "instanceID": 0
                                }
                            },
                            {
                                "buildingID": 0,
                                "buildingObject": {
                                    "instanceID": 0
                                }
                            }
                        ]
                    },
                    {
                        "floorNum": 5,
                        "floorSize": 7,
                        "buildings": [
                            {
                                "buildingID": 18,
                                "buildingObject": {
                                    "instanceID": 0
                                }
                            },
                            {
                                "buildingID": 19,
                                "buildingObject": {
                                    "instanceID": 0
                                }
                            },
                            {
                                "buildingID": 20,
                                "buildingObject": {
                                    "instanceID": 0
                                }
                            },
                            {
                                "buildingID": 21,
                                "buildingObject": {
                                    "instanceID": 0
                                }
                            },
                            {
                                "buildingID": 22,
                                "buildingObject": {
                                    "instanceID": 0
                                }
                            },
                            {
                                "buildingID": 0,
                                "buildingObject": {
                                    "instanceID": 0
                                }
                            }
                        ]
                    },
                    {
                        "floorNum": 6,
                        "floorSize": 6,
                        "buildings": [
                            {
                                "buildingID": 23,
                                "buildingObject": {
                                    "instanceID": 0
                                }
                            },
                            {
                                "buildingID": 0,
                                "buildingObject": {
                                    "instanceID": 0
                                }
                            },
                            {
                                "buildingID": 0,
                                "buildingObject": {
                                    "instanceID": 0
                                }
                            },
                            {
                                "buildingID": 0,
                                "buildingObject": {
                                    "instanceID": 0
                                }
                            },
                            {
                                "buildingID": 0,
                                "buildingObject": {
                                    "instanceID": 0
                                }
                            },
                            {
                                "buildingID": 0,
                                "buildingObject": {
                                    "instanceID": 0
                                }
                            }
                        ]
                    },
                    {
                        "floorNum": 0,
                        "floorSize": 0,
                        "buildings": []
                    },
                    {
                        "floorNum": 0,
                        "floorSize": 0,
                        "buildings": []
                    },
                    {
                        "floorNum": 0,
                        "floorSize": 0,
                        "buildings": []
                    }
                ]
            },
            "castleObject": {
                "instanceID": 0
            },
            "position": {
                "x": -1,
                "y": 2,
                "z": 0
            },
            "speed": 0.0,
            "_population": 25848.0,
            "_wood": 333787.71875,
            "_stone": 333701.71875,
            "_wheat": 333736.6875,
            "_gold": 333762.75,
            "_water": 0.0,
            "_taxRate": 3.0,
            "_happiness": 72.0
        },
        {
            "countryID": 4,
            "countryName": "ccc",
            "tower": {
                "floors": [
                    {
                        "floorNum": 0,
                        "floorSize": 12,
                        "buildings": [
                            {
                                "buildingID": 1,
                                "buildingObject": {
                                    "instanceID": 0
                                }
                            },
                            {
                                "buildingID": 2,
                                "buildingObject": {
                                    "instanceID": 0
                                }
                            },
                            {
                                "buildingID": 3,
                                "buildingObject": {
                                    "instanceID": 0
                                }
                            },
                            {
                                "buildingID": 0,
                                "buildingObject": {
                                    "instanceID": 0
                                }
                            },
                            {
                                "buildingID": 0,
                                "buildingObject": {
                                    "instanceID": 0
                                }
                            },
                            {
                                "buildingID": 0,
                                "buildingObject": {
                                    "instanceID": 0
                                }
                            }
                        ]
                    },
                    {
                        "floorNum": 1,
                        "floorSize": 11,
                        "buildings": [
                            {
                                "buildingID": 4,
                                "buildingObject": {
                                    "instanceID": 0
                                }
                            },
                            {
                                "buildingID": 5,
                                "buildingObject": {
                                    "instanceID": 0
                                }
                            },
                            {
                                "buildingID": 6,
                                "buildingObject": {
                                    "instanceID": 0
                                }
                            },
                            {
                                "buildingID": 7,
                                "buildingObject": {
                                    "instanceID": 0
                                }
                            },
                            {
                                "buildingID": 8,
                                "buildingObject": {
                                    "instanceID": 0
                                }
                            },
                            {
                                "buildingID": 9,
                                "buildingObject": {
                                    "instanceID": 0
                                }
                            }
                        ]
                    },
                    {
                        "floorNum": 2,
                        "floorSize": 10,
                        "buildings": [
                            {
                                "buildingID": 10,
                                "buildingObject": {
                                    "instanceID": 0
                                }
                            },
                            {
                                "buildingID": 11,
                                "buildingObject": {
                                    "instanceID": 0
                                }
                            },
                            {
                                "buildingID": 12,
                                "buildingObject": {
                                    "instanceID": 0
                                }
                            },
                            {
                                "buildingID": 13,
                                "buildingObject": {
                                    "instanceID": 0
                                }
                            },
                            {
                                "buildingID": 14,
                                "buildingObject": {
                                    "instanceID": 0
                                }
                            },
                            {
                                "buildingID": 0,
                                "buildingObject": {
                                    "instanceID": 0
                                }
                            }
                        ]
                    },
                    {
                        "floorNum": 3,
                        "floorSize": 9,
                        "buildings": [
                            {
                                "buildingID": 15,
                                "buildingObject": {
                                    "instanceID": 0
                                }
                            },
                            {
                                "buildingID": 16,
                                "buildingObject": {
                                    "instanceID": 0
                                }
                            },
                            {
                                "buildingID": 17,
                                "buildingObject": {
                                    "instanceID": 0
                                }
                            },
                            {
                                "buildingID": 18,
                                "buildingObject": {
                                    "instanceID": 0
                                }
                            },
                            {
                                "buildingID": 19,
                                "buildingObject": {
                                    "instanceID": 0
                                }
                            },
                            {
                                "buildingID": 0,
                                "buildingObject": {
                                    "instanceID": 0
                                }
                            }
                        ]
                    },
                    {
                        "floorNum": 4,
                        "floorSize": 8,
                        "buildings": [
                            {
                                "buildingID": 20,
                                "buildingObject": {
                                    "instanceID": 0
                                }
                            },
                            {
                                "buildingID": 21,
                                "buildingObject": {
                                    "instanceID": 0
                                }
                            },
                            {
                                "buildingID": 22,
                                "buildingObject": {
                                    "instanceID": 0
                                }
                            },
                            {
                                "buildingID": 23,
                                "buildingObject": {
                                    "instanceID": 0
                                }
                            },
                            {
                                "buildingID": 0,
                                "buildingObject": {
                                    "instanceID": 0
                                }
                            },
                            {
                                "buildingID": 0,
                                "buildingObject": {
                                    "instanceID": 0
                                }
                            }
                        ]
                    },
                    {
                        "floorNum": 0,
                        "floorSize": 0,
                        "buildings": []
                    },
                    {
                        "floorNum": 0,
                        "floorSize": 0,
                        "buildings": []
                    },
                    {
                        "floorNum": 0,
                        "floorSize": 0,
                        "buildings": []
                    },
                    {
                        "floorNum": 0,
                        "floorSize": 0,
                        "buildings": []
                    },
                    {
                        "floorNum": 0,
                        "floorSize": 0,
                        "buildings": []
                    }
                ]
            },
            "castleObject": {
                "instanceID": 0
            },
            "position": {
                "x": 0,
                "y": 1,
                "z": 0
            },
            "speed": 0.0,
            "_population": 23211.0,
            "_wood": 269402.65625,
            "_stone": 269455.6875,
            "_wheat": 269385.625,
            "_gold": 269420.6875,
            "_water": 0.0,
            "_taxRate": 45.0,
            "_happiness": 70.0
        },
        {
            "countryID": 2,
            "countryName": "d",
            "tower": {
                "floors": [
                    {
                        "floorNum": 0,
                        "floorSize": 12,
                        "buildings": [
                            {
                                "buildingID": 24,
                                "buildingObject": {
                                    "instanceID": 0
                                }
                            },
                            {
                                "buildingID": 25,
                                "buildingObject": {
                                    "instanceID": 0
                                }
                            },
                            {
                                "buildingID": 26,
                                "buildingObject": {
                                    "instanceID": 0
                                }
                            },
                            {
                                "buildingID": 27,
                                "buildingObject": {
                                    "instanceID": 0
                                }
                            },
                            {
                                "buildingID": 0,
                                "buildingObject": {
                                    "instanceID": 0
                                }
                            },
                            {
                                "buildingID": 0,
                                "buildingObject": {
                                    "instanceID": 0
                                }
                            }
                        ]
                    },
                    {
                        "floorNum": 1,
                        "floorSize": 11,
                        "buildings": [
                            {
                                "buildingID": 28,
                                "buildingObject": {
                                    "instanceID": 0
                                }
                            },
                            {
                                "buildingID": 29,
                                "buildingObject": {
                                    "instanceID": 0
                                }
                            },
                            {
                                "buildingID": 0,
                                "buildingObject": {
                                    "instanceID": 0
                                }
                            },
                            {
                                "buildingID": 0,
                                "buildingObject": {
                                    "instanceID": 0
                                }
                            },
                            {
                                "buildingID": 0,
                                "buildingObject": {
                                    "instanceID": 0
                                }
                            },
                            {
                                "buildingID": 0,
                                "buildingObject": {
                                    "instanceID": 0
                                }
                            }
                        ]
                    },
                    {
                        "floorNum": 2,
                        "floorSize": 10,
                        "buildings": [
                            {
                                "buildingID": 30,
                                "buildingObject": {
                                    "instanceID": 0
                                }
                            },
                            {
                                "buildingID": 31,
                                "buildingObject": {
                                    "instanceID": 0
                                }
                            },
                            {
                                "buildingID": 32,
                                "buildingObject": {
                                    "instanceID": 0
                                }
                            },
                            {
                                "buildingID": 33,
                                "buildingObject": {
                                    "instanceID": 0
                                }
                            },
                            {
                                "buildingID": 0,
                                "buildingObject": {
                                    "instanceID": 0
                                }
                            },
                            {
                                "buildingID": 0,
                                "buildingObject": {
                                    "instanceID": 0
                                }
                            }
                        ]
                    },
                    {
                        "floorNum": 3,
                        "floorSize": 9,
                        "buildings": [
                            {
                                "buildingID": 34,
                                "buildingObject": {
                                    "instanceID": 0
                                }
                            },
                            {
                                "buildingID": 0,
                                "buildingObject": {
                                    "instanceID": 0
                                }
                            },
                            {
                                "buildingID": 0,
                                "buildingObject": {
                                    "instanceID": 0
                                }
                            },
                            {
                                "buildingID": 0,
                                "buildingObject": {
                                    "instanceID": 0
                                }
                            },
                            {
                                "buildingID": 0,
                                "buildingObject": {
                                    "instanceID": 0
                                }
                            },
                            {
                                "buildingID": 0,
                                "buildingObject": {
                                    "instanceID": 0
                                }
                            }
                        ]
                    },
                    {
                        "floorNum": 4,
                        "floorSize": 8,
                        "buildings": [
                            {
                                "buildingID": 35,
                                "buildingObject": {
                                    "instanceID": 0
                                }
                            },
                            {
                                "buildingID": 36,
                                "buildingObject": {
                                    "instanceID": 0
                                }
                            },
                            {
                                "buildingID": 0,
                                "buildingObject": {
                                    "instanceID": 0
                                }
                            },
                            {
                                "buildingID": 0,
                                "buildingObject": {
                                    "instanceID": 0
                                }
                            },
                            {
                                "buildingID": 0,
                                "buildingObject": {
                                    "instanceID": 0
                                }
                            },
                            {
                                "buildingID": 0,
                                "buildingObject": {
                                    "instanceID": 0
                                }
                            }
                        ]
                    },
                    {
                        "floorNum": 5,
                        "floorSize": 7,
                        "buildings": [
                            {
                                "buildingID": 37,
                                "buildingObject": {
                                    "instanceID": 0
                                }
                            },
                            {
                                "buildingID": 38,
                                "buildingObject": {
                                    "instanceID": 0
                                }
                            },
                            {
                                "buildingID": 39,
                                "buildingObject": {
                                    "instanceID": 0
                                }
                            },
                            {
                                "buildingID": 40,
                                "buildingObject": {
                                    "instanceID": 0
                                }
                            },
                            {
                                "buildingID": 0,
                                "buildingObject": {
                                    "instanceID": 0
                                }
                            },
                            {
                                "buildingID": 0,
                                "buildingObject": {
                                    "instanceID": 0
                                }
                            }
                        ]
                    },
                    {
                        "floorNum": 6,
                        "floorSize": 6,
                        "buildings": [
                            {
                                "buildingID": 41,
                                "buildingObject": {
                                    "instanceID": 0
                                }
                            },
                            {
                                "buildingID": 42,
                                "buildingObject": {
                                    "instanceID": 0
                                }
                            },
                            {
                                "buildingID": 43,
                                "buildingObject": {
                                    "instanceID": 0
                                }
                            },
                            {
                                "buildingID": 0,
                                "buildingObject": {
                                    "instanceID": 0
                                }
                            },
                            {
                                "buildingID": 0,
                                "buildingObject": {
                                    "instanceID": 0
                                }
                            },
                            {
                                "buildingID": 0,
                                "buildingObject": {
                                    "instanceID": 0
                                }
                            }
                        ]
                    },
                    {
                        "floorNum": 7,
                        "floorSize": 5,
                        "buildings": [
                            {
                                "buildingID": 44,
                                "buildingObject": {
                                    "instanceID": 0
                                }
                            },
                            {
                                "buildingID": 0,
                                "buildingObject": {
                                    "instanceID": 0
                                }
                            },
                            {
                                "buildingID": 0,
                                "buildingObject": {
                                    "instanceID": 0
                                }
                            },
                            {
                                "buildingID": 0,
                                "buildingObject": {
                                    "instanceID": 0
                                }
                            },
                            {
                                "buildingID": 0,
                                "buildingObject": {
                                    "instanceID": 0
                                }
                            },
                            {
                                "buildingID": 0,
                                "buildingObject": {
                                    "instanceID": 0
                                }
                            }
                        ]
                    },
                    {
                        "floorNum": 0,
                        "floorSize": 0,
                        "buildings": []
                    },
                    {
                        "floorNum": 0,
                        "floorSize": 0,
                        "buildings": []
                    }
                ]
            },
            "castleObject": {
                "instanceID": 0
            },
            "position": {
                "x": 1,
                "y": -2,
                "z": 0
            },
            "speed": 0.0,
            "_population": 23313.0,
            "_wood": 271825.0,
            "_stone": 271757.96875,
            "_wheat": 271805.84375,
            "_gold": 271769.96875,
            "_water": 0.0,
            "_taxRate": 29.0,
            "_happiness": 22.0
        },
        {
            "countryID": 3,
            "countryName": "k",
            "tower": {
                "floors": [
                    {
                        "floorNum": 0,
                        "floorSize": 12,
                        "buildings": [
                            {
                                "buildingID": 1,
                                "buildingObject": {
                                    "instanceID": 0
                                }
                            },
                            {
                                "buildingID": 0,
                                "buildingObject": {
                                    "instanceID": 0
                                }
                            },
                            {
                                "buildingID": 0,
                                "buildingObject": {
                                    "instanceID": 0
                                }
                            },
                            {
                                "buildingID": 0,
                                "buildingObject": {
                                    "instanceID": 0
                                }
                            },
                            {
                                "buildingID": 0,
                                "buildingObject": {
                                    "instanceID": 0
                                }
                            },
                            {
                                "buildingID": 0,
                                "buildingObject": {
                                    "instanceID": 0
                                }
                            }
                        ]
                    },
                    {
                        "floorNum": 1,
                        "floorSize": 11,
                        "buildings": [
                            {
                                "buildingID": 2,
                                "buildingObject": {
                                    "instanceID": 0
                                }
                            },
                            {
                                "buildingID": 0,
                                "buildingObject": {
                                    "instanceID": 0
                                }
                            },
                            {
                                "buildingID": 0,
                                "buildingObject": {
                                    "instanceID": 0
                                }
                            },
                            {
                                "buildingID": 0,
                                "buildingObject": {
                                    "instanceID": 0
                                }
                            },
                            {
                                "buildingID": 0,
                                "buildingObject": {
                                    "instanceID": 0
                                }
                            },
                            {
                                "buildingID": 0,
                                "buildingObject": {
                                    "instanceID": 0
                                }
                            }
                        ]
                    },
                    {
                        "floorNum": 2,
                        "floorSize": 10,
                        "buildings": [
                            {
                                "buildingID": 3,
                                "buildingObject": {
                                    "instanceID": 0
                                }
                            },
                            {
                                "buildingID": 4,
                                "buildingObject": {
                                    "instanceID": 0
                                }
                            },
                            {
                                "buildingID": 5,
                                "buildingObject": {
                                    "instanceID": 0
                                }
                            },
                            {
                                "buildingID": 6,
                                "buildingObject": {
                                    "instanceID": 0
                                }
                            },
                            {
                                "buildingID": 0,
                                "buildingObject": {
                                    "instanceID": 0
                                }
                            },
                            {
                                "buildingID": 0,
                                "buildingObject": {
                                    "instanceID": 0
                                }
                            }
                        ]
                    },
                    {
                        "floorNum": 3,
                        "floorSize": 9,
                        "buildings": [
                            {
                                "buildingID": 7,
                                "buildingObject": {
                                    "instanceID": 0
                                }
                            },
                            {
                                "buildingID": 8,
                                "buildingObject": {
                                    "instanceID": 0
                                }
                            },
                            {
                                "buildingID": 9,
                                "buildingObject": {
                                    "instanceID": 0
                                }
                            },
                            {
                                "buildingID": 10,
                                "buildingObject": {
                                    "instanceID": 0
                                }
                            },
                            {
                                "buildingID": 11,
                                "buildingObject": {
                                    "instanceID": 0
                                }
                            },
                            {
                                "buildingID": 0,
                                "buildingObject": {
                                    "instanceID": 0
                                }
                            }
                        ]
                    },
                    {
                        "floorNum": 4,
                        "floorSize": 8,
                        "buildings": [
                            {
                                "buildingID": 12,
                                "buildingObject": {
                                    "instanceID": 0
                                }
                            },
                            {
                                "buildingID": 13,
                                "buildingObject": {
                                    "instanceID": 0
                                }
                            },
                            {
                                "buildingID": 14,
                                "buildingObject": {
                                    "instanceID": 0
                                }
                            },
                            {
                                "buildingID": 0,
                                "buildingObject": {
                                    "instanceID": 0
                                }
                            },
                            {
                                "buildingID": 0,
                                "buildingObject": {
                                    "instanceID": 0
                                }
                            },
                            {
                                "buildingID": 0,
                                "buildingObject": {
                                    "instanceID": 0
                                }
                            }
                        ]
                    },
                    {
                        "floorNum": 0,
                        "floorSize": 0,
                        "buildings": []
                    },
                    {
                        "floorNum": 0,
                        "floorSize": 0,
                        "buildings": []
                    },
                    {
                        "floorNum": 0,
                        "floorSize": 0,
                        "buildings": []
                    },
                    {
                        "floorNum": 0,
                        "floorSize": 0,
                        "buildings": []
                    },
                    {
                        "floorNum": 0,
                        "floorSize": 0,
                        "buildings": []
                    }
                ]
            },
            "castleObject": {
                "instanceID": 0
            },
            "position": {
                "x": -1,
                "y": 0,
                "z": 0
            },
            "speed": 0.0,
            "_population": 23356.0,
            "_wood": 272780.46875,
            "_stone": 272757.46875,
            "_wheat": 272756.625,
            "_gold": 272756.46875,
            "_water": 0.0,
            "_taxRate": 48.0,
            "_happiness": 99.0
        }
    ],
    "gold": 0,
    "gems": 0,
    "countryCounter": 1
}